onepitranslator/__init__.py
onepitranslator/__main__.py
onepitranslator/choose_translate.py
onepitranslator/create_shortcut.py
onepitranslator/install_offline_translator_language.py
onepitranslator/onepi.py
onepitranslator/languages/ar.msg
onepitranslator/languages/de.msg
onepitranslator/languages/es.msg
onepitranslator/languages/fr.msg
onepitranslator/languages/hi.msg
onepitranslator/languages/it.msg
onepitranslator/languages/ja.msg
onepitranslator/languages/ko.msg
onepitranslator/languages/pl.msg
onepitranslator/languages/pt.msg
onepitranslator/languages/ru.msg
onepitranslator/languages/th.msg
onepitranslator/languages/tr.msg
onepitranslator/languages/zh_cn.msg
onepitranslator/languages/zh_tw.msg
onepitranslator/resources/images/123.png
onepitranslator/resources/images/CUDAandNV.jpg
onepitranslator/resources/images/all.gif
onepitranslator/resources/images/cnshow1.png
onepitranslator/resources/images/cnshow2.png
onepitranslator/resources/images/cnshow3.png
onepitranslator/resources/images/cnshow4.png
onepitranslator/resources/images/cnshow5.png
onepitranslator/resources/images/cnshow6.png
onepitranslator/resources/images/cuda-time.png
onepitranslator/resources/images/enshow1.png
onepitranslator/resources/images/enshow2.png
onepitranslator/resources/images/enshow3.png
onepitranslator/resources/images/enshow4.png
onepitranslator/resources/images/enshow5.png
onepitranslator/resources/images/enshow6.png
onepitranslator/resources/images/icon.png
onepitranslator/resources/images/jp.png
onepitranslator/resources/images/jp2.png
onepitranslator/resources/images/ko.png
onepitranslator/resources/images/onepi512.ico
onepitranslator/resources/images/百度云小程序.png
onepitranslator/scripts/install_argos_language.bat
onepitranslator/scripts/install_argos_translate.bat
onepitranslator/scripts/movefile.bat
onepitranslator/scripts/run.bat
onepitranslator/scripts/run_this_to_upgrade_modules.bat
onepitranslator-1.0.0.data/data/share/onepitranslator/run.sh
onepitranslator-1.0.0.dist-info/LICENSE
onepitranslator-1.0.0.dist-info/METADATA
onepitranslator-1.0.0.dist-info/WHEEL
onepitranslator-1.0.0.dist-info/entry_points.txt
onepitranslator-1.0.0.dist-info/top_level.txt
onepitranslator-1.0.0.dist-info/RECORD
