Metadata-Version: 2.1
Name: onepitranslator
Version: 1.0.0
Summary: A simple GUI tool for translating text or documents and renaming files or folder names using both online and offline methods.
Home-page: https://github.com/OnePi-1pi/OnePiTranslator
Author: One Pi
Author-email: q_o_ql@163.com
Classifier: Development Status :: 5 - Production/Stable
Classifier: Intended Audience :: End Users/Desktop
Classifier: License :: OSI Approved :: Apache Software License
Classifier: Programming Language :: Python :: 3.9
Classifier: Programming Language :: Python :: 3.10
Classifier: Programming Language :: Python :: 3.11
Classifier: Programming Language :: Python :: 3.12
Classifier: Programming Language :: Python :: 3.13
Classifier: Programming Language :: Python :: 3.14
Classifier: Programming Language :: Python :: 3 :: Only
Classifier: Operating System :: OS Independent
Requires-Python: >=3.7
License-File: LICENSE
Requires-Dist: setuptools
Requires-Dist: ttkbootstrap
Requires-Dist: pillow
Requires-Dist: qrcode
Requires-Dist: deep-translator
Requires-Dist: regex
Requires-Dist: deep-translator[ai]
Requires-Dist: deep-translator[docx]
Requires-Dist: deep-translator[pdf]
Provides-Extra: complete
Requires-Dist: argostranslate ; extra == 'complete'
Requires-Dist: spacy ; extra == 'complete'
Requires-Dist: spacy[xx_sent_ud_sm] ; extra == 'complete'
